faim/__init__.py
faim/fairlearn_api.py
faim/main.py
faim/algorithm/__init__.py
faim/algorithm/faim.py
faim/data_preparation/__init__.py
faim/data_preparation/compas.py
faim/data_preparation/synthetic.py
faim/data_preparation/zalando.py
faim/evaluation/__init__.py
faim/evaluation/compas.py
faim/evaluation/synthetic.py
faim/evaluation/zalando.py
faim/util/__init__.py
faim/util/util.py
faim/visualization/__init__.py
faim/visualization/compasBinPlots.py
faim/visualization/plots.py
faim-0.3.0.dist-info/LICENSE
faim-0.3.0.dist-info/METADATA
faim-0.3.0.dist-info/WHEEL
faim-0.3.0.dist-info/entry_points.txt
faim-0.3.0.dist-info/top_level.txt
faim-0.3.0.dist-info/zip-safe
faim-0.3.0.dist-info/RECORD
