Metadata-Version: 2.1
Name: faim
Version: 0.3.0
Summary: FAIM (FAir Interpolation Method), described in "Beyond Incompatibility: Interpolation between Mutually
Author: Meike Zehlike, Alex Loosley
Author-email: meike.zehlike@zalando.de, aloosley@alumni.brown.edu
License: Apache License Version 2.0
Project-URL: Paper, https://arxiv.org/pdf/2206.03256
Project-URL: Code Repository, https://github.com/MilkaLichtblau/faim
Keywords: fairness,optimal transport
Classifier: Programming Language :: Python :: 3
Requires-Python: >=3.9
License-File: LICENSE
Requires-Dist: pot >=0.8.0
Requires-Dist: pandas >=1.5.0
Requires-Dist: scikit-learn >=1.0.0
Requires-Dist: seaborn >=0.13.2
Requires-Dist: fairlearn >=0.10.0
Provides-Extra: dev
Requires-Dist: pre-commit >=2.20.0 ; extra == 'dev'
Requires-Dist: pytest >=7.0.0 ; extra == 'dev'
Requires-Dist: pytest-cov >=3.0.0 ; extra == 'dev'
Provides-Extra: experiment
Requires-Dist: jupyter >=1.0.0 ; extra == 'experiment'
Requires-Dist: lxml >=4.9.1 ; extra == 'experiment'
Requires-Dist: matplotlib >=3.5.0 ; extra == 'experiment'
Requires-Dist: statsmodels >=0.13.5 ; extra == 'experiment'
Requires-Dist: plotly >=5.11.0 ; extra == 'experiment'
Requires-Dist: pooch >=1.6.0 ; extra == 'experiment'
Provides-Extra: fairlearn_api
Requires-Dist: fairlearn >=0.10.0 ; extra == 'fairlearn_api'
